{
  "timestamp": 1742902641.7671256,
  "episodes": [
    {
      "name": "Episode 1",
      "serie_name": "One Piece",
      "season_name": "Kai - Saga 2 (Alabasta)",
      "index": 1,
      "streaming_links": [
        {
          "language": "vostfr",
          "players": [
            "https://vidmoly.to/embed-udbmp57ujoad.html",
            "https://video.sibnet.ru/shell.php?videoid=4776133"
          ]
        },
        {
          "language": "vf",
          "players": [
            "https://www.myvi.tv/embed/jg6f7xsdbn9rpgi7hb9wpxqshh",
            "https://video.sibnet.ru/shell.php?videoid=4838992"
          ]
        }
      ]
    },
    {
      "name": "Episode 2",
      "serie_name": "One Piece",
      "season_name": "Kai - Saga 2 (Alabasta)",
      "index": 2,
      "streaming_links": [
        {
          "language": "vostfr",
          "players": [
            "https://vidmoly.to/embed-5x9vg2biswsw.html",
            "https://video.sibnet.ru/shell.php?videoid=4774058"
          ]
        },
        {
          "language": "vf",
          "players": [
            "https://www.myvi.tv/embed/1mea5iq1u9xrdbnr5znbc1pn4y",
            "https://video.sibnet.ru/shell.php?videoid=4838999"
          ]
        }
      ]
    },
    {
      "name": "Episode 3",
      "serie_name": "One Piece",
      "season_name": "Kai - Saga 2 (Alabasta)",
      "index": 3,
      "streaming_links": [
        {
          "language": "vostfr",
          "players": [
            "https://vidmoly.to/embed-k6z7lggxiuyj.html",
            "https://video.sibnet.ru/shell.php?videoid=4774060"
          ]
        },
        {
          "language": "vf",
          "players": [
            "https://www.myvi.tv/embed/gjywbozxfz6r7dayt16yi9e5sh",
            "https://video.sibnet.ru/shell.php?videoid=4839002"
          ]
        }
      ]
    },
    {
      "name": "Episode 4",
      "serie_name": "One Piece",
      "season_name": "Kai - Saga 2 (Alabasta)",
      "index": 4,
      "streaming_links": [
        {
          "language": "vostfr",
          "players": [
            "https://vidmoly.to/embed-xp4i03p4mln7.html",
            "https://video.sibnet.ru/shell.php?videoid=4774063"
          ]
        },
        {
          "language": "vf",
          "players": [
            "https://www.myvi.tv/embed/e3xhxh6odp9rtmf6r11rjbimth",
            "https://video.sibnet.ru/shell.php?videoid=4839006"
          ]
        }
      ]
    },
    {
      "name": "Episode 5",
      "serie_name": "One Piece",
      "season_name": "Kai - Saga 2 (Alabasta)",
      "index": 5,
      "streaming_links": [
        {
          "language": "vostfr",
          "players": [
            "https://vidmoly.to/embed-ez7r6e9m0i30.html",
            "https://video.sibnet.ru/shell.php?videoid=4774069"
          ]
        },
        {
          "language": "vf",
          "players": [
            "https://www.myvi.tv/embed/yqy74dhsttxwbr95uhktmrfdsy",
            "https://video.sibnet.ru/shell.php?videoid=4839009"
          ]
        }
      ]
    },
    {
      "name": "Episode 6",
      "serie_name": "One Piece",
      "season_name": "Kai - Saga 2 (Alabasta)",
      "index": 6,
      "streaming_links": [
        {
          "language": "vostfr",
          "players": [
            "https://vidmoly.to/embed-cpathv82a2fw.html",
            "https://video.sibnet.ru/shell.php?videoid=4774075"
          ]
        },
        {
          "language": "vf",
          "players": [
            "https://www.myvi.tv/embed/7c5yjqzhpi4rmqj7gpq5ujyaqe",
            "https://video.sibnet.ru/shell.php?videoid=4839012"
          ]
        }
      ]
    },
    {
      "name": "Episode 7",
      "serie_name": "One Piece",
      "season_name": "Kai - Saga 2 (Alabasta)",
      "index": 7,
      "streaming_links": [
        {
          "language": "vostfr",
          "players": [
            "https://vidmoly.to/embed-thh3l9uy1mop.html",
            "https://video.sibnet.ru/shell.php?videoid=4774079"
          ]
        },
        {
          "language": "vf",
          "players": [
            "https://www.myvi.tv/embed/bedajhxqinjrbqed5n885553fr",
            "https://video.sibnet.ru/shell.php?videoid=4839015"
          ]
        }
      ]
    },
    {
      "name": "Episode 8",
      "serie_name": "One Piece",
      "season_name": "Kai - Saga 2 (Alabasta)",
      "index": 8,
      "streaming_links": [
        {
          "language": "vostfr",
          "players": [
            "https://vidmoly.to/embed-swecx2cj0rg9.html",
            "https://video.sibnet.ru/shell.php?videoid=4774081"
          ]
        },
        {
          "language": "vf",
          "players": [
            "https://www.myvi.tv/embed/7tpe6nsby1gw8pjym4bp5ogy8c",
            "https://video.sibnet.ru/shell.php?videoid=4839017"
          ]
        }
      ]
    },
    {
      "name": "Episode 9",
      "serie_name": "One Piece",
      "season_name": "Kai - Saga 2 (Alabasta)",
      "index": 9,
      "streaming_links": [
        {
          "language": "vostfr",
          "players": [
            "https://vidmoly.to/embed-houbkvvbw2m1.html",
            "https://video.sibnet.ru/shell.php?videoid=4774092\t"
          ]
        },
        {
          "language": "vf",
          "players": [
            "https://www.myvi.tv/embed/unnzejmr7certxz8m9cqmrnoqr\t",
            "https://video.sibnet.ru/shell.php?videoid=4839019"
          ]
        }
      ]
    }
  ]
}